boxdrive/__init__.py
boxdrive/_create_app.py
boxdrive/constants.py
boxdrive/dependencies.py
boxdrive/exceptions.py
boxdrive/handlers.py
boxdrive/middleware.py
boxdrive/py.typed
boxdrive/s3.py
boxdrive/store.py
boxdrive/version.py
boxdrive/schemas/__init__.py
boxdrive/schemas/store.py
boxdrive/schemas/xml.py
boxdrive/stores/__init__.py
boxdrive/stores/_utils.py
boxdrive/stores/inmemory.py
boxdrive/stores/gitlab/__init__.py
boxdrive/stores/gitlab/client.py
boxdrive/stores/gitlab/store.py
boxdrive-0.0.4.dist-info/METADATA
boxdrive-0.0.4.dist-info/WHEEL
boxdrive-0.0.4.dist-info/licenses/LICENSE
boxdrive-0.0.4.dist-info/RECORD
