Metadata-Version: 2.4
Name: boxdrive
Version: 0.0.4
Summary: S3-compatible API with Abstract Object Store in Python (FastAPI).
Author-email: Alex Severin <severinalexeyv@gmail.com>
License-File: LICENSE
Requires-Python: >=3.12
Requires-Dist: aiorwlock>=1.5.0
Requires-Dist: fastapi[standard]>=0.115.14
Requires-Dist: opentelemetry-exporter-otlp>=1.35.0
Requires-Dist: opentelemetry-instrumentation-fastapi>=0.55b1
Requires-Dist: opentelemetry-instrumentation-httpx>=0.56b0
Requires-Dist: opentelemetry-instrumentation-logging>=0.55b1
Requires-Dist: opentelemetry-sdk>=1.34.1
Requires-Dist: pydantic-xml>=2.17.2
Requires-Dist: pydantic>=2.11.7
